mmidata/__init__.py
mmidata/count.py
mmidata/main.py
mmidata/size.py
mmidata/utils/__init__.py
mmidata/utils/aws.py
mmidata-0.1.3.dist-info/entry_points.txt
mmidata-0.1.3.dist-info/WHEEL
mmidata-0.1.3.dist-info/METADATA
mmidata-0.1.3.dist-info/RECORD
